summing_lixelv/__init__.py
summing_lixelv/main.py
summing_lixelv-0.0.5.dist-info/METADATA
summing_lixelv-0.0.5.dist-info/WHEEL
summing_lixelv-0.0.5.dist-info/licenses/LICENSE
summing_lixelv-0.0.5.dist-info/RECORD
